keyrings/tmp/gcp_auth.py
keyrings.tmp.gcp_artifact_registry_auth-0.0.2.dist-info/LICENSE
keyrings.tmp.gcp_artifact_registry_auth-0.0.2.dist-info/METADATA
keyrings.tmp.gcp_artifact_registry_auth-0.0.2.dist-info/WHEEL
keyrings.tmp.gcp_artifact_registry_auth-0.0.2.dist-info/entry_points.txt
keyrings.tmp.gcp_artifact_registry_auth-0.0.2.dist-info/top_level.txt
keyrings.tmp.gcp_artifact_registry_auth-0.0.2.dist-info/RECORD
